switchkey/api/models/auth.py
switchkey/api/models/organization.py
switchkey/api/models/project.py
switchkey/api/models/user.py
switchkey/api/request/request.py
switchkey/api/request/types.py
switchkey/api/response/response.py
switchkey/api/response/types.py
switchkey/api/routes.py
switchkey/api/types.py
switchkey/core/base.py
switchkey/core/exceptions.py
switchkey/utils/config.py
switchkey/utils/decorators.py
switchkey/utils/logger.py
switchkey/utils/parser.py
switchkey-0.1.1.dist-info/METADATA
switchkey-0.1.1.dist-info/WHEEL
switchkey-0.1.1.dist-info/RECORD
